eons/__init__.py
eons/eons.py
eons/method/External.py
eons/method/__init__.py
eons/resolve/__init__.py
eons/resolve/resolve_find_by_fetch.py
eons/resolve/resolve_import_module.py
eons/resolve/resolve_install_from_repo.py
eons/resolve/resolve_install_from_repo_with_default_package_type.py
eons/resolve/resolve_install_with_pip.py
eons/resolve/resolve_namespace_lookup.py
eons/resolve/resolve_observe.py
eons-3.1.6.dist-info/METADATA
eons-3.1.6.dist-info/WHEEL
eons-3.1.6.dist-info/top_level.txt
eons-3.1.6.dist-info/RECORD
