Metadata-Version: 2.1
Name: eons
Version: 3.1.6
Summary: Eons Python Framework
Home-page: https://github.com/eons-dev/eons.lib
Author: Eons
Author-email: support@eons.llc
Project-URL: Bug Tracker, https://github.com/eons-dev/eons.lib/issues
Classifier: Programming Language :: Python :: 3
Classifier: License :: OSI Approved :: MIT License
Classifier: Operating System :: OS Independent
Classifier: Development Status :: 4 - Beta
Requires-Python: >=3.7
Requires-Dist: tqdm
Requires-Dist: eot
Requires-Dist: requests-futures
Requires-Dist: pyyaml
Requires-Dist: jsonpickle
Requires-Dist: requests
